explorer.py
maxcli.py
maxsmart_http.py
MaxSmart_CLI-1.0.2.dist-info/DESCRIPTION.rst
MaxSmart_CLI-1.0.2.dist-info/METADATA
MaxSmart_CLI-1.0.2.dist-info/RECORD
MaxSmart_CLI-1.0.2.dist-info/WHEEL
MaxSmart_CLI-1.0.2.dist-info/entry_points.txt
MaxSmart_CLI-1.0.2.dist-info/metadata.json
MaxSmart_CLI-1.0.2.dist-info/top_level.txt
