Metadata-Version: 2.0
Name: MaxSmart-CLI
Version: 1.0.2
Summary: UNKNOWN
Home-page: https://github.com/phylor/maxcli
Author: Serge Hänni
Author-email: serge@nyi.ch
License: UNKNOWN
Platform: UNKNOWN
Requires-Dist: Click
Requires-Dist: requests
